gertty/__init__.py
gertty/alembic.ini
gertty/app.py
gertty/auth.py
gertty/commentlink.py
gertty/config.py
gertty/db.py
gertty/dbsupport.py
gertty/gitrepo.py
gertty/keymap.py
gertty/mywid.py
gertty/palette.py
gertty/requestsexceptions.py
gertty/sync.py
gertty/version.py
gertty/alembic/README
gertty/alembic/env.py
gertty/alembic/script.py.mako
gertty/alembic/versions/1bb187bcd401_add_query_sync_table.py
gertty/alembic/versions/1cdd4e2e74c_add_revision_indexes.py
gertty/alembic/versions/254ac5fc3941_attach_comments_to_files.py
gertty/alembic/versions/2a11dd14665_fix_account_table.py
gertty/alembic/versions/312cd5a9f878_add_can_submit_column.py
gertty/alembic/versions/3610c2543e07_add_conflicts_table.py
gertty/alembic/versions/37a702b7f58e_add_last_seen_column_to_change.py
gertty/alembic/versions/38104b4c1b84_added_project_updated_column.py
gertty/alembic/versions/3cc7e3753dc3_add_hold.py
gertty/alembic/versions/3d429503a29a_add_draft_fields.py
gertty/alembic/versions/4388de50824a_add_topic_table.py
gertty/alembic/versions/44402069e137_initial_schema.py
gertty/alembic/versions/46b175bfa277_add_pending_actions.py
gertty/alembic/versions/4a802b741d2f_add_starred.py
gertty/alembic/versions/4cc9c46f9d8b_add_account_table.py
gertty/alembic/versions/50344aecd1c2_add_files_table.py
gertty/alembic/versions/56e48a4a064a_increase_status_field_width.py
gertty/alembic/versions/725816dc500_add_fetch_ref_column.py
gertty/alembic/versions/7ef7dfa2ca3a_add_change_outdated.py
gertty/search/__init__.py
gertty/search/parser.py
gertty/search/tokenizer.py
gertty/view/__init__.py
gertty/view/change.py
gertty/view/change_list.py
gertty/view/diff.py
gertty/view/mouse_scroll_decorator.py
gertty/view/project_list.py
gertty/view/side_diff.py
gertty/view/unified_diff.py
gertty-1.6.0.data/data/share/gertty/examples/googlesource-gertty.yaml
gertty-1.6.0.data/data/share/gertty/examples/minimal-gertty.yaml
gertty-1.6.0.data/data/share/gertty/examples/opendev-gertty.yaml
gertty-1.6.0.dist-info/AUTHORS
gertty-1.6.0.dist-info/LICENSE
gertty-1.6.0.dist-info/METADATA
gertty-1.6.0.dist-info/WHEEL
gertty-1.6.0.dist-info/entry_points.txt
gertty-1.6.0.dist-info/pbr.json
gertty-1.6.0.dist-info/top_level.txt
gertty-1.6.0.dist-info/RECORD
