Metadata-Version: 2.1
Name: gertty
Version: 1.6.0
Summary: Gertty is a console-based interface to the Gerrit Code Review system.
Home-page: http://ttygroup.org/
Author: The TTY Group
Author-email: openstack-infra@lists.openstack.org
License: UNKNOWN
Keywords: gerrit console urwid review
Platform: UNKNOWN
Classifier: Topic :: Utilities
Classifier: Intended Audience :: Developers
Classifier: Intended Audience :: Information Technology
Classifier: Intended Audience :: System Administrators
Classifier: License :: OSI Approved :: Apache Software License
Classifier: Operating System :: POSIX :: Linux
Classifier: Programming Language :: Python
Classifier: Programming Language :: Python :: 2
Classifier: Programming Language :: Python :: 2.7
Requires-Dist: pbr (>=0.11)
Requires-Dist: urwid (!=1.3.0,>=1.2.1)
Requires-Dist: SQLAlchemy (>=1.0.4)
Requires-Dist: GitPython (>=0.3.7)
Requires-Dist: python-dateutil
Requires-Dist: requests (<3.0.0,>=2.5.3)
Requires-Dist: ordereddict
Requires-Dist: alembic (>=0.6.4)
Requires-Dist: PyYAML (>=3.1.0)
Requires-Dist: voluptuous (>=0.7)
Requires-Dist: ply (>=3.4)
Requires-Dist: six
